xtml/__init__.py
xtml/utils.py
xtml/tensorflow/__init__.py
xtml/torch/__init__.py
xtml/torch/datamodel.py
xtml-0.0.4.dist-info/LICENSE
xtml-0.0.4.dist-info/METADATA
xtml-0.0.4.dist-info/WHEEL
xtml-0.0.4.dist-info/top_level.txt
xtml-0.0.4.dist-info/RECORD
