Metadata-Version: 2.1
Name: xtml
Version: 0.0.4
Summary: A machine learning trainer across various ML frameworks.
Author-email: Seungbae Ji <seungbae.ji@email.com>
License: GNU GENERAL PUBLIC LICENSE
Project-URL: homepage, https://github.com/seungbaeji/xtml
Project-URL: repository, https://github.com/seungbaeji/xtml
Classifier: Programming Language :: Python :: 3
Classifier: License :: OSI Approved :: GNU General Public License v3 (GPLv3)
Classifier: Operating System :: OS Independent
License-File: LICENSE
Requires-Dist: tensorflow >=2.4.0
Requires-Dist: torch >=1.8.0
Provides-Extra: tensorflow
Requires-Dist: tensorflow >=2.4.0 ; extra == 'tensorflow'
Provides-Extra: torch
Requires-Dist: torch >=1.8.0 ; extra == 'torch'
